maxbot/__init__.py
maxbot/__main__.py
maxbot/_download.py
maxbot/_hooks.py
maxbot/bot.py
maxbot/builder.py
maxbot/channels/__init__.py
maxbot/channels/_manager.py
maxbot/channels/facebook.py
maxbot/channels/telegram.py
maxbot/channels/viber.py
maxbot/channels/vk.py
maxbot/cli/__init__.py
maxbot/cli/_bot.py
maxbot/cli/_journal.py
maxbot/cli/_logging.py
maxbot/cli/_ngrok.py
maxbot/cli/_rich.py
maxbot/cli/_yaml_dumper.py
maxbot/cli/info.py
maxbot/cli/run.py
maxbot/cli/stories.py
maxbot/context.py
maxbot/dialog_manager.py
maxbot/errors.py
maxbot/extensions/__init__.py
maxbot/extensions/_manager.py
maxbot/extensions/babel.py
maxbot/extensions/datetime.py
maxbot/extensions/jinja_loader.py
maxbot/extensions/rasa.py
maxbot/extensions/rest.py
maxbot/flows/__init__.py
maxbot/flows/_base.py
maxbot/flows/dialog_flow.py
maxbot/flows/dialog_tree.py
maxbot/flows/slot_filling.py
maxbot/jinja_env.py
maxbot/maxml/__init__.py
maxbot/maxml/http.py
maxbot/maxml/markup.py
maxbot/maxml/pretty.py
maxbot/maxml/timedelta.py
maxbot/maxml/xml_parser.py
maxbot/nlu.py
maxbot/persistence_manager.py
maxbot/resolver.py
maxbot/resources.py
maxbot/rpc.py
maxbot/scenarios.py
maxbot/schemas.py
maxbot/stories/__init__.py
maxbot/stories/pytest.py
maxbot/user_locks/__init__.py
maxbot/user_locks/asyncio.py
maxbot/user_locks/mp.py
maxbot/webapp.py
maxbot-0.3.0b2.dist-info/LICENSE
maxbot-0.3.0b2.dist-info/METADATA
maxbot-0.3.0b2.dist-info/WHEEL
maxbot-0.3.0b2.dist-info/entry_points.txt
maxbot-0.3.0b2.dist-info/RECORD
