Metadata-Version: 2.1
Name: Maxbot
Version: 0.3.0b2
Summary: Maxbot is an open source library and framework for creating conversational apps.
Home-page: https://maxbot.ai
License: MIT
Keywords: maxbot,conversational-apps,nlp,conversational-ai,bot,chatbot,text-bot,voice-bot,botkit,chatbot-framework
Author: Maxbot team
Author-email: hello@maxbot.ai
Maintainer: Maxbot team
Maintainer-email: hello@maxbot.ai
Requires-Python: >=3.9,<3.12
Classifier: Development Status :: 4 - Beta
Classifier: Intended Audience :: Developers
Classifier: License :: OSI Approved :: MIT License
Classifier: Operating System :: MacOS :: MacOS X
Classifier: Operating System :: POSIX :: Linux
Classifier: Programming Language :: Python :: 3
Classifier: Programming Language :: Python :: 3.9
Classifier: Programming Language :: Python :: 3.10
Classifier: Programming Language :: Python :: 3.11
Classifier: Topic :: Software Development :: Libraries
Requires-Dist: Babel (>=2.9,<2.13)
Requires-Dist: Jinja2 (>=3.1,<4.0)
Requires-Dist: MarkupSafe (>=2.1.2,<3.0.0)
Requires-Dist: PyYAML (>=6.0,<7.0)
Requires-Dist: SQLAlchemy (>=1.4.36,<3.0)
Requires-Dist: click (>=8.1,<9.0)
Requires-Dist: dateparser (>=1.1,<2.0)
Requires-Dist: defusedxml (>=0.7.1,<0.8.0)
Requires-Dist: httpx (>=0.23,<0.24)
Requires-Dist: markdown-it-py (>=2.1.0,<3.0.0)
Requires-Dist: marshmallow (>=3.19,<4.0)
Requires-Dist: number-parser (>=0.3,<0.4)
Requires-Dist: python-dateutil (>=2.8,<3.0)
Requires-Dist: python-dotenv (>=1.0,<2.0)
Requires-Dist: python-telegram-bot[ujson] (>=20.1,<21.0)
Requires-Dist: regex (<=2023.4.0)
Requires-Dist: rich (>=13.3,<14.0)
Requires-Dist: sanic (>=21.12,<22.13)
Requires-Dist: spacy (>=3.5,<4.0)
Requires-Dist: textdistance (>=4.5,<5.0)
Requires-Dist: viberbot (>=1.0,<2.0)
Requires-Dist: websockets (>=10,<11)
Project-URL: Documentation, https://maxbot.ai/intro
Project-URL: Repository, https://github.com/maxbot-ai/maxbot
